{
  "schema_version": 2,
  "description": "Measured efficiency for TopHNT ID",
  "corrections": [
    {
      "name": "data",
      "description": "",
      "version": 1,
      "inputs": [
        {
          "name": "abseta",
          "type": "real",
          "description": "abseta"
        },
        {
          "name": "pt",
          "type": "real",
          "description": "pt"
        },
        {
          "name": "syst",
          "type": "string",
          "description": "systematic variation (nom, up, down)"
        }
      ],
      "output": {
        "name": "eff_data",
        "type": "real",
        "description": "eff_data"
      },
      "generic_formulas": null,
      "data": {
        "nodetype": "category",
        "input": "syst",
        "content": [
          {
            "key": "nom",
            "value": {
              "nodetype": "binning",
              "input": "abseta",
              "edges": [
                0.0,
                0.8999999761581421,
                1.2000000476837158,
                2.0999999046325684,
                2.4000000953674316
              ],
              "content": [
                {
                  "nodetype": "binning",
                  "input": "pt",
                  "edges": [
                    10.0,
                    15.0,
                    20.0,
                    25.0,
                    30.0,
                    40.0,
                    50.0,
                    60.0,
                    120.0,
                    200.0
                  ],
                  "content": [
                    0.743996,
                    0.778134,
                    0.83519,
                    0.892892,
                    0.937581,
                    0.960969,
                    0.965831,
                    0.967963,
                    0.971446
                  ],
                  "flow": "clamp"
                },
                {
                  "nodetype": "binning",
                  "input": "pt",
                  "edges": [
                    10.0,
                    15.0,
                    20.0,
                    25.0,
                    30.0,
                    40.0,
                    50.0,
                    60.0,
                    120.0,
                    200.0
                  ],
                  "content": [
                    0.766607,
                    0.787509,
                    0.827692,
                    0.875835,
                    0.918961,
                    0.950115,
                    0.955288,
                    0.95585,
                    0.955166
                  ],
                  "flow": "clamp"
                },
                {
                  "nodetype": "binning",
                  "input": "pt",
                  "edges": [
                    10.0,
                    15.0,
                    20.0,
                    25.0,
                    30.0,
                    40.0,
                    50.0,
                    60.0,
                    120.0,
                    200.0
                  ],
                  "content": [
                    0.761906,
                    0.783453,
                    0.812216,
                    0.860684,
                    0.899617,
                    0.926982,
                    0.934212,
                    0.934352,
                    0.923362
                  ],
                  "flow": "clamp"
                },
                {
                  "nodetype": "binning",
                  "input": "pt",
                  "edges": [
                    10.0,
                    15.0,
                    20.0,
                    25.0,
                    30.0,
                    40.0,
                    50.0,
                    60.0,
                    120.0,
                    200.0
                  ],
                  "content": [
                    0.709397,
                    0.724607,
                    0.755177,
                    0.793256,
                    0.828449,
                    0.854866,
                    0.869414,
                    0.86404,
                    0.849758
                  ],
                  "flow": "clamp"
                }
              ],
              "flow": "clamp"
            }
          },
          {
            "key": "up",
            "value": {
              "nodetype": "binning",
              "input": "abseta",
              "edges": [
                0.0,
                0.8999999761581421,
                1.2000000476837158,
                2.0999999046325684,
                2.4000000953674316
              ],
              "content": [
                {
                  "nodetype": "binning",
                  "input": "pt",
                  "edges": [
                    10.0,
                    15.0,
                    20.0,
                    25.0,
                    30.0,
                    40.0,
                    50.0,
                    60.0,
                    120.0,
                    200.0
                  ],
                  "content": [
                    0.7622029056404431,
                    0.7942418795314591,
                    0.8394940782985443,
                    0.8974892495037795,
                    0.9378015311769342,
                    0.9615999548319809,
                    0.9662361357797085,
                    0.9687223931787948,
                    0.9735210575895623
                  ],
                  "flow": "clamp"
                },
                {
                  "nodetype": "binning",
                  "input": "pt",
                  "edges": [
                    10.0,
                    15.0,
                    20.0,
                    25.0,
                    30.0,
                    40.0,
                    50.0,
                    60.0,
                    120.0,
                    200.0
                  ],
                  "content": [
                    0.782054759708126,
                    0.8021325137364451,
                    0.834177672131707,
                    0.8794530031785504,
                    0.920511597304267,
                    0.9505173630201696,
                    0.9559879642848031,
                    0.9570241528861269,
                    0.9683078339283374
                  ],
                  "flow": "clamp"
                },
                {
                  "nodetype": "binning",
                  "input": "pt",
                  "edges": [
                    10.0,
                    15.0,
                    20.0,
                    25.0,
                    30.0,
                    40.0,
                    50.0,
                    60.0,
                    120.0,
                    200.0
                  ],
                  "content": [
                    0.7722345004235852,
                    0.7949685730643333,
                    0.8215091859983538,
                    0.8651585655655046,
                    0.9003439215913701,
                    0.9274230022675678,
                    0.9354979583974609,
                    0.9363780609566348,
                    0.9400102313475036
                  ],
                  "flow": "clamp"
                },
                {
                  "nodetype": "binning",
                  "input": "pt",
                  "edges": [
                    10.0,
                    15.0,
                    20.0,
                    25.0,
                    30.0,
                    40.0,
                    50.0,
                    60.0,
                    120.0,
                    200.0
                  ],
                  "content": [
                    0.7170223407136994,
                    0.7319677062161182,
                    0.7577770813448813,
                    0.7972348798675004,
                    0.8300178062340519,
                    0.8560993085583097,
                    0.8736485391720942,
                    0.8730804617691797,
                    0.9103036211050807
                  ],
                  "flow": "clamp"
                }
              ],
              "flow": "clamp"
            }
          },
          {
            "key": "down",
            "value": {
              "nodetype": "binning",
              "input": "abseta",
              "edges": [
                0.0,
                0.8999999761581421,
                1.2000000476837158,
                2.0999999046325684,
                2.4000000953674316
              ],
              "content": [
                {
                  "nodetype": "binning",
                  "input": "pt",
                  "edges": [
                    10.0,
                    15.0,
                    20.0,
                    25.0,
                    30.0,
                    40.0,
                    50.0,
                    60.0,
                    120.0,
                    200.0
                  ],
                  "content": [
                    0.7257890943595569,
                    0.7620261204685409,
                    0.8308859217014557,
                    0.8882947504962205,
                    0.9373604688230658,
                    0.960338045168019,
                    0.9654258642202915,
                    0.9672036068212052,
                    0.9693709424104378
                  ],
                  "flow": "clamp"
                },
                {
                  "nodetype": "binning",
                  "input": "pt",
                  "edges": [
                    10.0,
                    15.0,
                    20.0,
                    25.0,
                    30.0,
                    40.0,
                    50.0,
                    60.0,
                    120.0,
                    200.0
                  ],
                  "content": [
                    0.7511592402918741,
                    0.7728854862635549,
                    0.821206327868293,
                    0.8722169968214497,
                    0.917410402695733,
                    0.9497126369798304,
                    0.9545880357151969,
                    0.9546758471138731,
                    0.9420241660716625
                  ],
                  "flow": "clamp"
                },
                {
                  "nodetype": "binning",
                  "input": "pt",
                  "edges": [
                    10.0,
                    15.0,
                    20.0,
                    25.0,
                    30.0,
                    40.0,
                    50.0,
                    60.0,
                    120.0,
                    200.0
                  ],
                  "content": [
                    0.7515774995764147,
                    0.7719374269356666,
                    0.8029228140016463,
                    0.8562094344344954,
                    0.8988900784086299,
                    0.9265409977324321,
                    0.9329260416025392,
                    0.9323259390433651,
                    0.9067137686524964
                  ],
                  "flow": "clamp"
                },
                {
                  "nodetype": "binning",
                  "input": "pt",
                  "edges": [
                    10.0,
                    15.0,
                    20.0,
                    25.0,
                    30.0,
                    40.0,
                    50.0,
                    60.0,
                    120.0,
                    200.0
                  ],
                  "content": [
                    0.7017716592863007,
                    0.7172462937838818,
                    0.7525769186551187,
                    0.7892771201324995,
                    0.8268801937659481,
                    0.8536326914416903,
                    0.8651794608279059,
                    0.8549995382308203,
                    0.7892123788949194
                  ],
                  "flow": "clamp"
                }
              ],
              "flow": "clamp"
            }
          }
        ],
        "default": null
      }
    },
    {
      "name": "sim",
      "description": "",
      "version": 1,
      "inputs": [
        {
          "name": "abseta",
          "type": "real",
          "description": "abseta"
        },
        {
          "name": "pt",
          "type": "real",
          "description": "pt"
        },
        {
          "name": "syst",
          "type": "string",
          "description": "systematic variation (nom, up, down)"
        }
      ],
      "output": {
        "name": "eff_mc",
        "type": "real",
        "description": "eff_mc"
      },
      "generic_formulas": null,
      "data": {
        "nodetype": "category",
        "input": "syst",
        "content": [
          {
            "key": "nom",
            "value": {
              "nodetype": "binning",
              "input": "abseta",
              "edges": [
                0.0,
                0.8999999761581421,
                1.2000000476837158,
                2.0999999046325684,
                2.4000000953674316
              ],
              "content": [
                {
                  "nodetype": "binning",
                  "input": "pt",
                  "edges": [
                    10.0,
                    15.0,
                    20.0,
                    25.0,
                    30.0,
                    40.0,
                    50.0,
                    60.0,
                    120.0,
                    200.0
                  ],
                  "content": [
                    0.786208,
                    0.818747,
                    0.864393,
                    0.909799,
                    0.948273,
                    0.969171,
                    0.972396,
                    0.974225,
                    0.975864
                  ],
                  "flow": "clamp"
                },
                {
                  "nodetype": "binning",
                  "input": "pt",
                  "edges": [
                    10.0,
                    15.0,
                    20.0,
                    25.0,
                    30.0,
                    40.0,
                    50.0,
                    60.0,
                    120.0,
                    200.0
                  ],
                  "content": [
                    0.808426,
                    0.831712,
                    0.86046,
                    0.898232,
                    0.937698,
                    0.963702,
                    0.966561,
                    0.967196,
                    0.968209
                  ],
                  "flow": "clamp"
                },
                {
                  "nodetype": "binning",
                  "input": "pt",
                  "edges": [
                    10.0,
                    15.0,
                    20.0,
                    25.0,
                    30.0,
                    40.0,
                    50.0,
                    60.0,
                    120.0,
                    200.0
                  ],
                  "content": [
                    0.798634,
                    0.822263,
                    0.852745,
                    0.889237,
                    0.924378,
                    0.948037,
                    0.952845,
                    0.954313,
                    0.954661
                  ],
                  "flow": "clamp"
                },
                {
                  "nodetype": "binning",
                  "input": "pt",
                  "edges": [
                    10.0,
                    15.0,
                    20.0,
                    25.0,
                    30.0,
                    40.0,
                    50.0,
                    60.0,
                    120.0,
                    200.0
                  ],
                  "content": [
                    0.756976,
                    0.784477,
                    0.816198,
                    0.848751,
                    0.877227,
                    0.898989,
                    0.905923,
                    0.906338,
                    0.901166
                  ],
                  "flow": "clamp"
                }
              ],
              "flow": "clamp"
            }
          },
          {
            "key": "up",
            "value": {
              "nodetype": "binning",
              "input": "abseta",
              "edges": [
                0.0,
                0.8999999761581421,
                1.2000000476837158,
                2.0999999046325684,
                2.4000000953674316
              ],
              "content": [
                {
                  "nodetype": "binning",
                  "input": "pt",
                  "edges": [
                    10.0,
                    15.0,
                    20.0,
                    25.0,
                    30.0,
                    40.0,
                    50.0,
                    60.0,
                    120.0,
                    200.0
                  ],
                  "content": [
                    0.8030809880578398,
                    0.832616387729817,
                    0.8682640426244101,
                    0.9114879434567208,
                    0.9490336917904119,
                    0.9694396466080187,
                    0.9728550359463048,
                    0.9746795349271508,
                    0.97709093683619
                  ],
                  "flow": "clamp"
                },
                {
                  "nodetype": "binning",
                  "input": "pt",
                  "edges": [
                    10.0,
                    15.0,
                    20.0,
                    25.0,
                    30.0,
                    40.0,
                    50.0,
                    60.0,
                    120.0,
                    200.0
                  ],
                  "content": [
                    0.819150877108853,
                    0.8442846472152845,
                    0.8672707183908895,
                    0.9012255113161637,
                    0.9391090187808814,
                    0.9640709661231062,
                    0.9674680683546458,
                    0.9682885978217075,
                    0.9704489651783007
                  ],
                  "flow": "clamp"
                },
                {
                  "nodetype": "binning",
                  "input": "pt",
                  "edges": [
                    10.0,
                    15.0,
                    20.0,
                    25.0,
                    30.0,
                    40.0,
                    50.0,
                    60.0,
                    120.0,
                    200.0
                  ],
                  "content": [
                    0.8070664650607043,
                    0.8320989521653981,
                    0.8600655447884703,
                    0.893167660758702,
                    0.926050685864112,
                    0.948403599236224,
                    0.9540487337745531,
                    0.9561612453841414,
                    0.9585510651665492
                  ],
                  "flow": "clamp"
                },
                {
                  "nodetype": "binning",
                  "input": "pt",
                  "edges": [
                    10.0,
                    15.0,
                    20.0,
                    25.0,
                    30.0,
                    40.0,
                    50.0,
                    60.0,
                    120.0,
                    200.0
                  ],
                  "content": [
                    0.7629175720983592,
                    0.7904799181237128,
                    0.8187034883755467,
                    0.8511357800737175,
                    0.87908402611721,
                    0.8995578769638507,
                    0.9076869331053076,
                    0.911923018621276,
                    0.9291894632406489
                  ],
                  "flow": "clamp"
                }
              ],
              "flow": "clamp"
            }
          },
          {
            "key": "down",
            "value": {
              "nodetype": "binning",
              "input": "abseta",
              "edges": [
                0.0,
                0.8999999761581421,
                1.2000000476837158,
                2.0999999046325684,
                2.4000000953674316
              ],
              "content": [
                {
                  "nodetype": "binning",
                  "input": "pt",
                  "edges": [
                    10.0,
                    15.0,
                    20.0,
                    25.0,
                    30.0,
                    40.0,
                    50.0,
                    60.0,
                    120.0,
                    200.0
                  ],
                  "content": [
                    0.7693350119421603,
                    0.804877612270183,
                    0.8605219573755898,
                    0.9081100565432793,
                    0.9475123082095882,
                    0.9689023533919813,
                    0.9719369640536952,
                    0.9737704650728493,
                    0.9746370631638099
                  ],
                  "flow": "clamp"
                },
                {
                  "nodetype": "binning",
                  "input": "pt",
                  "edges": [
                    10.0,
                    15.0,
                    20.0,
                    25.0,
                    30.0,
                    40.0,
                    50.0,
                    60.0,
                    120.0,
                    200.0
                  ],
                  "content": [
                    0.7977011228911469,
                    0.8191393527847155,
                    0.8536492816091105,
                    0.8952384886838364,
                    0.9362869812191187,
                    0.9633330338768937,
                    0.9656539316453542,
                    0.9661034021782924,
                    0.9659690348216993
                  ],
                  "flow": "clamp"
                },
                {
                  "nodetype": "binning",
                  "input": "pt",
                  "edges": [
                    10.0,
                    15.0,
                    20.0,
                    25.0,
                    30.0,
                    40.0,
                    50.0,
                    60.0,
                    120.0,
                    200.0
                  ],
                  "content": [
                    0.7902015349392956,
                    0.8124270478346018,
                    0.8454244552115296,
                    0.8853063392412981,
                    0.9227053141358881,
                    0.9476704007637761,
                    0.951641266225447,
                    0.9524647546158586,
                    0.9507709348334508
                  ],
                  "flow": "clamp"
                },
                {
                  "nodetype": "binning",
                  "input": "pt",
                  "edges": [
                    10.0,
                    15.0,
                    20.0,
                    25.0,
                    30.0,
                    40.0,
                    50.0,
                    60.0,
                    120.0,
                    200.0
                  ],
                  "content": [
                    0.7510344279016408,
                    0.7784740818762872,
                    0.8136925116244532,
                    0.8463662199262826,
                    0.8753699738827899,
                    0.8984201230361494,
                    0.9041590668946925,
                    0.900752981378724,
                    0.8731425367593512
                  ],
                  "flow": "clamp"
                }
              ],
              "flow": "clamp"
            }
          }
        ],
        "default": null
      }
    },
    {
      "name": "sf",
      "description": "",
      "version": 1,
      "inputs": [
        {
          "name": "abseta",
          "type": "real",
          "description": "abseta"
        },
        {
          "name": "pt",
          "type": "real",
          "description": "pt"
        },
        {
          "name": "syst",
          "type": "string",
          "description": "systematic variation (nom, up, down)"
        }
      ],
      "output": {
        "name": "sf",
        "type": "real",
        "description": "sf"
      },
      "generic_formulas": null,
      "data": {
        "nodetype": "category",
        "input": "syst",
        "content": [
          {
            "key": "nom",
            "value": {
              "nodetype": "binning",
              "input": "abseta",
              "edges": [
                0.0,
                0.8999999761581421,
                1.2000000476837158,
                2.0999999046325684,
                2.4000000953674316
              ],
              "content": [
                {
                  "nodetype": "binning",
                  "input": "pt",
                  "edges": [
                    10.0,
                    15.0,
                    20.0,
                    25.0,
                    30.0,
                    40.0,
                    50.0,
                    60.0,
                    120.0,
                    200.0
                  ],
                  "content": [
                    0.9463093736008791,
                    0.9503961541233128,
                    0.9662155986917987,
                    0.9814167744743619,
                    0.9887247659692936,
                    0.991537097168611,
                    0.9932486353296394,
                    0.99357232672124,
                    0.9954727298066125
                  ],
                  "flow": "clamp"
                },
                {
                  "nodetype": "binning",
                  "input": "pt",
                  "edges": [
                    10.0,
                    15.0,
                    20.0,
                    25.0,
                    30.0,
                    40.0,
                    50.0,
                    60.0,
                    120.0,
                    200.0
                  ],
                  "content": [
                    0.948271084799351,
                    0.9468529971913354,
                    0.9619180438370174,
                    0.9750654619296574,
                    0.9800180868467246,
                    0.9859012433304072,
                    0.9883370009756239,
                    0.9882691822546826,
                    0.9865287350148573
                  ],
                  "flow": "clamp"
                },
                {
                  "nodetype": "binning",
                  "input": "pt",
                  "edges": [
                    10.0,
                    15.0,
                    20.0,
                    25.0,
                    30.0,
                    40.0,
                    50.0,
                    60.0,
                    120.0,
                    200.0
                  ],
                  "content": [
                    0.9540114745928674,
                    0.9528009894644414,
                    0.9524723100106128,
                    0.9678904499025569,
                    0.973213339131827,
                    0.9777909511970524,
                    0.9804448782330809,
                    0.9790833824960993,
                    0.9672145400304402
                  ],
                  "flow": "clamp"
                },
                {
                  "nodetype": "binning",
                  "input": "pt",
                  "edges": [
                    10.0,
                    15.0,
                    20.0,
                    25.0,
                    30.0,
                    40.0,
                    50.0,
                    60.0,
                    120.0,
                    200.0
                  ],
                  "content": [
                    0.937145959713386,
                    0.9236816375750978,
                    0.9252375036449489,
                    0.9346156882289387,
                    0.9443952363527343,
                    0.9509193104698722,
                    0.9596996654241033,
                    0.9533308765604003,
                    0.9429539063835076
                  ],
                  "flow": "clamp"
                }
              ],
              "flow": "clamp"
            }
          },
          {
            "key": "up",
            "value": {
              "nodetype": "binning",
              "input": "abseta",
              "edges": [
                0.0,
                0.8999999761581421,
                1.2000000476837158,
                2.0999999046325684,
                2.4000000953674316
              ],
              "content": [
                {
                  "nodetype": "binning",
                  "input": "pt",
                  "edges": [
                    10.0,
                    15.0,
                    20.0,
                    25.0,
                    30.0,
                    40.0,
                    50.0,
                    60.0,
                    120.0,
                    200.0
                  ],
                  "content": [
                    0.9552108375180989,
                    0.9545641242744399,
                    0.97153787807398,
                    0.9870582100052648,
                    0.9896013607317062,
                    0.9919904856309313,
                    0.9936600543598757,
                    0.994247901933211,
                    0.9978808808747254
                  ],
                  "flow": "clamp"
                },
                {
                  "nodetype": "binning",
                  "input": "pt",
                  "edges": [
                    10.0,
                    15.0,
                    20.0,
                    25.0,
                    30.0,
                    40.0,
                    50.0,
                    60.0,
                    120.0,
                    200.0
                  ],
                  "content": [
                    0.9582873942159068,
                    0.9512341080399124,
                    0.9692711738763631,
                    0.9800607669454551,
                    0.9817208264020464,
                    0.986265785138162,
                    0.9892186496310357,
                    0.9888859421489753,
                    1.0001333490501074
                  ],
                  "flow": "clamp"
                },
                {
                  "nodetype": "binning",
                  "input": "pt",
                  "edges": [
                    10.0,
                    15.0,
                    20.0,
                    25.0,
                    30.0,
                    40.0,
                    50.0,
                    60.0,
                    120.0,
                    200.0
                  ],
                  "content": [
                    0.9580553341088793,
                    0.9560434045773406,
                    0.9590277269035604,
                    0.9765631083027143,
                    0.9754855110018852,
                    0.9782896572983041,
                    0.9809644270289111,
                    0.9795885429057483,
                    0.982963428154786
                  ],
                  "flow": "clamp"
                },
                {
                  "nodetype": "binning",
                  "input": "pt",
                  "edges": [
                    10.0,
                    15.0,
                    20.0,
                    25.0,
                    30.0,
                    40.0,
                    50.0,
                    60.0,
                    120.0,
                    200.0
                  ],
                  "content": [
                    0.9423452173871295,
                    0.9274575428640507,
                    0.9272575611159849,
                    0.9396900411688062,
                    0.9474685114350931,
                    0.9523543058583696,
                    0.9628217241779348,
                    0.9576455861792039,
                    0.9903107670635268
                  ],
                  "flow": "clamp"
                }
              ],
              "flow": "clamp"
            }
          },
          {
            "key": "down",
            "value": {
              "nodetype": "binning",
              "input": "abseta",
              "edges": [
                0.0,
                0.8999999761581421,
                1.2000000476837158,
                2.0999999046325684,
                2.4000000953674316
              ],
              "content": [
                {
                  "nodetype": "binning",
                  "input": "pt",
                  "edges": [
                    10.0,
                    15.0,
                    20.0,
                    25.0,
                    30.0,
                    40.0,
                    50.0,
                    60.0,
                    120.0,
                    200.0
                  ],
                  "content": [
                    0.9374079096836593,
                    0.9462281839721857,
                    0.9608933193096175,
                    0.975775338943459,
                    0.987848171206881,
                    0.9910837087062908,
                    0.992837216299403,
                    0.9928967515092689,
                    0.9930645787384996
                  ],
                  "flow": "clamp"
                },
                {
                  "nodetype": "binning",
                  "input": "pt",
                  "edges": [
                    10.0,
                    15.0,
                    20.0,
                    25.0,
                    30.0,
                    40.0,
                    50.0,
                    60.0,
                    120.0,
                    200.0
                  ],
                  "content": [
                    0.9382547753827951,
                    0.9424718863427585,
                    0.9545649137976717,
                    0.9700701569138597,
                    0.9783153472914029,
                    0.9855367015226524,
                    0.9874553523202122,
                    0.98765242236039,
                    0.9729241209796071
                  ],
                  "flow": "clamp"
                },
                {
                  "nodetype": "binning",
                  "input": "pt",
                  "edges": [
                    10.0,
                    15.0,
                    20.0,
                    25.0,
                    30.0,
                    40.0,
                    50.0,
                    60.0,
                    120.0,
                    200.0
                  ],
                  "content": [
                    0.9499676150768555,
                    0.9495585743515421,
                    0.9459168931176652,
                    0.9592177915023995,
                    0.9709411672617687,
                    0.9772922450958007,
                    0.9799253294372507,
                    0.9785782220864503,
                    0.9514656519060943
                  ],
                  "flow": "clamp"
                },
                {
                  "nodetype": "binning",
                  "input": "pt",
                  "edges": [
                    10.0,
                    15.0,
                    20.0,
                    25.0,
                    30.0,
                    40.0,
                    50.0,
                    60.0,
                    120.0,
                    200.0
                  ],
                  "content": [
                    0.9319467020396425,
                    0.9199057322861449,
                    0.923217446173913,
                    0.9295413352890712,
                    0.9413219612703754,
                    0.9494843150813749,
                    0.9565776066702719,
                    0.9490161669415966,
                    0.8955970457034884
                  ],
                  "flow": "clamp"
                }
              ],
              "flow": "clamp"
            }
          }
        ],
        "default": null
      }
    }
  ],
  "compound_corrections": null
}