{
  "schema_version": 2,
  "description": "Measured efficiency for Mu8El23_El23Leg Trigger path",
  "corrections": [
    {
      "name": "Mu8El23_Data",
      "description": "",
      "version": 1,
      "inputs": [
        {
          "name": "abssceta",
          "type": "real",
          "description": "abssceta"
        },
        {
          "name": "pt",
          "type": "real",
          "description": "pt"
        },
        {
          "name": "syst",
          "type": "string",
          "description": "systematic variation (nom, up, down)"
        }
      ],
      "output": {
        "name": "eff_data",
        "type": "real",
        "description": "eff_data"
      },
      "generic_formulas": null,
      "data": {
        "nodetype": "category",
        "input": "syst",
        "content": [
          {
            "key": "nom",
            "value": {
              "nodetype": "binning",
              "input": "abssceta",
              "edges": [
                0.0,
                0.800000011920929,
                1.4789999723434448,
                2.5
              ],
              "content": [
                {
                  "nodetype": "binning",
                  "input": "pt",
                  "edges": [
                    10.0,
                    20.0,
                    23.0,
                    25.0,
                    30.0,
                    40.0,
                    50.0,
                    100.0,
                    200.0
                  ],
                  "content": [
                    0.0005055611729019212,
                    0.03162827020695041,
                    0.6259196378041879,
                    0.9105581708137189,
                    0.9389527458492976,
                    0.9534429431873678,
                    0.9685977616853193,
                    0.9798068481123793
                  ],
                  "flow": "clamp"
                },
                {
                  "nodetype": "binning",
                  "input": "pt",
                  "edges": [
                    10.0,
                    20.0,
                    23.0,
                    25.0,
                    30.0,
                    40.0,
                    50.0,
                    100.0,
                    200.0
                  ],
                  "content": [
                    0.0,
                    0.045454545454545456,
                    0.5500467726847521,
                    0.9031296572280179,
                    0.9391545687446626,
                    0.9611185086551265,
                    0.9623087308730873,
                    0.9789964994165694
                  ],
                  "flow": "clamp"
                },
                {
                  "nodetype": "binning",
                  "input": "pt",
                  "edges": [
                    10.0,
                    20.0,
                    23.0,
                    25.0,
                    30.0,
                    40.0,
                    50.0,
                    100.0,
                    200.0
                  ],
                  "content": [
                    0.002705836876691148,
                    0.09529553679131483,
                    0.5893536121673004,
                    0.9019448946515397,
                    0.9490890940853506,
                    0.9531303455354089,
                    0.970358306188925,
                    0.9778820375335121
                  ],
                  "flow": "clamp"
                }
              ],
              "flow": "clamp"
            }
          },
          {
            "key": "up",
            "value": {
              "nodetype": "binning",
              "input": "abssceta",
              "edges": [
                0.0,
                0.800000011920929,
                1.4789999723434448,
                2.5
              ],
              "content": [
                {
                  "nodetype": "binning",
                  "input": "pt",
                  "edges": [
                    10.0,
                    20.0,
                    23.0,
                    25.0,
                    30.0,
                    40.0,
                    50.0,
                    100.0,
                    200.0
                  ],
                  "content": [
                    0.001124796796909265,
                    0.03524023269671239,
                    0.6515848733117182,
                    0.930770405024909,
                    0.9542028820577743,
                    0.9710215036353297,
                    0.9798159724403589,
                    1.000460386792077
                  ],
                  "flow": "clamp"
                },
                {
                  "nodetype": "binning",
                  "input": "pt",
                  "edges": [
                    10.0,
                    20.0,
                    23.0,
                    25.0,
                    30.0,
                    40.0,
                    50.0,
                    100.0,
                    200.0
                  ],
                  "content": [
                    0.0,
                    0.0512339283358641,
                    0.5787888769533671,
                    0.928521189022977,
                    0.9588937302309153,
                    0.9836361117686472,
                    0.9769754347478828,
                    1.0064627544802576
                  ],
                  "flow": "clamp"
                },
                {
                  "nodetype": "binning",
                  "input": "pt",
                  "edges": [
                    10.0,
                    20.0,
                    23.0,
                    25.0,
                    30.0,
                    40.0,
                    50.0,
                    100.0,
                    200.0
                  ],
                  "content": [
                    0.0038469694919856428,
                    0.10343588503810648,
                    0.6192016522315654,
                    0.930142412128842,
                    0.9705836340967736,
                    0.9783705970936827,
                    0.9880753671660287,
                    1.0140606862689643
                  ],
                  "flow": "clamp"
                }
              ],
              "flow": "clamp"
            }
          },
          {
            "key": "down",
            "value": {
              "nodetype": "binning",
              "input": "abssceta",
              "edges": [
                0.0,
                0.800000011920929,
                1.4789999723434448,
                2.5
              ],
              "content": [
                {
                  "nodetype": "binning",
                  "input": "pt",
                  "edges": [
                    10.0,
                    20.0,
                    23.0,
                    25.0,
                    30.0,
                    40.0,
                    50.0,
                    100.0,
                    200.0
                  ],
                  "content": [
                    -0.0001136744511054229,
                    0.02801630771718842,
                    0.6002544022966576,
                    0.8903459366025288,
                    0.9237026096408208,
                    0.9358643827394059,
                    0.9573795509302797,
                    0.9591533094326816
                  ],
                  "flow": "clamp"
                },
                {
                  "nodetype": "binning",
                  "input": "pt",
                  "edges": [
                    10.0,
                    20.0,
                    23.0,
                    25.0,
                    30.0,
                    40.0,
                    50.0,
                    100.0,
                    200.0
                  ],
                  "content": [
                    0.0,
                    0.03967516257322681,
                    0.5213046684161371,
                    0.8777381254330587,
                    0.91941540725841,
                    0.9386009055416058,
                    0.9476420269982918,
                    0.9515302443528812
                  ],
                  "flow": "clamp"
                },
                {
                  "nodetype": "binning",
                  "input": "pt",
                  "edges": [
                    10.0,
                    20.0,
                    23.0,
                    25.0,
                    30.0,
                    40.0,
                    50.0,
                    100.0,
                    200.0
                  ],
                  "content": [
                    0.0015647042613966535,
                    0.08715518854452318,
                    0.5595055721030354,
                    0.8737473771742374,
                    0.9275945540739275,
                    0.9278900939771351,
                    0.9526412452118214,
                    0.9417033887980599
                  ],
                  "flow": "clamp"
                }
              ],
              "flow": "clamp"
            }
          }
        ],
        "default": null
      }
    },
    {
      "name": "Mu8El23_MC",
      "description": "",
      "version": 1,
      "inputs": [
        {
          "name": "abssceta",
          "type": "real",
          "description": "abssceta"
        },
        {
          "name": "pt",
          "type": "real",
          "description": "pt"
        },
        {
          "name": "syst",
          "type": "string",
          "description": "systematic variation (nom, up, down)"
        }
      ],
      "output": {
        "name": "eff_mc",
        "type": "real",
        "description": "eff_mc"
      },
      "generic_formulas": null,
      "data": {
        "nodetype": "category",
        "input": "syst",
        "content": [
          {
            "key": "nom",
            "value": {
              "nodetype": "binning",
              "input": "abssceta",
              "edges": [
                0.0,
                0.800000011920929,
                1.4789999723434448,
                2.5
              ],
              "content": [
                {
                  "nodetype": "binning",
                  "input": "pt",
                  "edges": [
                    10.0,
                    20.0,
                    23.0,
                    25.0,
                    30.0,
                    40.0,
                    50.0,
                    100.0,
                    200.0
                  ],
                  "content": [
                    0.0003198843240200345,
                    0.046826723066889675,
                    0.7571312214479581,
                    0.9118262036868912,
                    0.9349362459948378,
                    0.9494908565508842,
                    0.9677530918562249,
                    0.9867775807102176
                  ],
                  "flow": "clamp"
                },
                {
                  "nodetype": "binning",
                  "input": "pt",
                  "edges": [
                    10.0,
                    20.0,
                    23.0,
                    25.0,
                    30.0,
                    40.0,
                    50.0,
                    100.0,
                    200.0
                  ],
                  "content": [
                    0.0006820838934700772,
                    0.06810733673546653,
                    0.7076454134339129,
                    0.9182187660224175,
                    0.9443687306453539,
                    0.9526178542284733,
                    0.9658983689395869,
                    0.9850156254944434
                  ],
                  "flow": "clamp"
                },
                {
                  "nodetype": "binning",
                  "input": "pt",
                  "edges": [
                    10.0,
                    20.0,
                    23.0,
                    25.0,
                    30.0,
                    40.0,
                    50.0,
                    100.0,
                    200.0
                  ],
                  "content": [
                    0.0019171042703941322,
                    0.07468777207989771,
                    0.5937124707297732,
                    0.9171597726884317,
                    0.953500727255865,
                    0.9656120560568964,
                    0.979285672581687,
                    0.9857772946930755
                  ],
                  "flow": "clamp"
                }
              ],
              "flow": "clamp"
            }
          },
          {
            "key": "up",
            "value": {
              "nodetype": "binning",
              "input": "abssceta",
              "edges": [
                0.0,
                0.800000011920929,
                1.4789999723434448,
                2.5
              ],
              "content": [
                {
                  "nodetype": "binning",
                  "input": "pt",
                  "edges": [
                    10.0,
                    20.0,
                    23.0,
                    25.0,
                    30.0,
                    40.0,
                    50.0,
                    100.0,
                    200.0
                  ],
                  "content": [
                    0.0006626442792469728,
                    0.07080900977753272,
                    0.768890587957793,
                    0.9335790000162307,
                    0.9467168925121688,
                    0.9557182695491525,
                    0.9705155677487872,
                    1.0008514698989517
                  ],
                  "flow": "clamp"
                },
                {
                  "nodetype": "binning",
                  "input": "pt",
                  "edges": [
                    10.0,
                    20.0,
                    23.0,
                    25.0,
                    30.0,
                    40.0,
                    50.0,
                    100.0,
                    200.0
                  ],
                  "content": [
                    0.0021478998334910865,
                    0.08240859889187595,
                    0.7266028667934774,
                    0.9337484350282055,
                    0.9504182881039254,
                    0.9825397108005881,
                    1.038103327511773,
                    1.0013180369004666
                  ],
                  "flow": "clamp"
                },
                {
                  "nodetype": "binning",
                  "input": "pt",
                  "edges": [
                    10.0,
                    20.0,
                    23.0,
                    25.0,
                    30.0,
                    40.0,
                    50.0,
                    100.0,
                    200.0
                  ],
                  "content": [
                    0.0041168185863046675,
                    0.11036961302744686,
                    0.6282872827527212,
                    0.9394572470405427,
                    0.9876169856015531,
                    0.9882773130772333,
                    1.0129988552877665,
                    1.0025413399141243
                  ],
                  "flow": "clamp"
                }
              ],
              "flow": "clamp"
            }
          },
          {
            "key": "down",
            "value": {
              "nodetype": "binning",
              "input": "abssceta",
              "edges": [
                0.0,
                0.800000011920929,
                1.4789999723434448,
                2.5
              ],
              "content": [
                {
                  "nodetype": "binning",
                  "input": "pt",
                  "edges": [
                    10.0,
                    20.0,
                    23.0,
                    25.0,
                    30.0,
                    40.0,
                    50.0,
                    100.0,
                    200.0
                  ],
                  "content": [
                    -2.2875631206903857e-05,
                    0.02284443635624663,
                    0.7453718549381232,
                    0.8900734073575516,
                    0.9231555994775068,
                    0.9432634435526158,
                    0.9649906159636626,
                    0.9727036915214835
                  ],
                  "flow": "clamp"
                },
                {
                  "nodetype": "binning",
                  "input": "pt",
                  "edges": [
                    10.0,
                    20.0,
                    23.0,
                    25.0,
                    30.0,
                    40.0,
                    50.0,
                    100.0,
                    200.0
                  ],
                  "content": [
                    -0.000783732046550932,
                    0.05380607457905711,
                    0.6886879600743483,
                    0.9026890970166295,
                    0.9383191731867824,
                    0.9226959976563586,
                    0.8936934103674008,
                    0.9687132140884203
                  ],
                  "flow": "clamp"
                },
                {
                  "nodetype": "binning",
                  "input": "pt",
                  "edges": [
                    10.0,
                    20.0,
                    23.0,
                    25.0,
                    30.0,
                    40.0,
                    50.0,
                    100.0,
                    200.0
                  ],
                  "content": [
                    -0.00028261004551640356,
                    0.03900593113234857,
                    0.5591376587068252,
                    0.8948622983363208,
                    0.9193844689101769,
                    0.9429467990365594,
                    0.9455724898756074,
                    0.9690132494720266
                  ],
                  "flow": "clamp"
                }
              ],
              "flow": "clamp"
            }
          }
        ],
        "default": null
      }
    }
  ],
  "compound_corrections": null
}