{
  "schema_version": 2,
  "description": "Measured efficiency for Mu23El12_Mu23Leg Trigger path",
  "corrections": [
    {
      "name": "Mu23El12_Data",
      "description": "",
      "version": 1,
      "inputs": [
        {
          "name": "abseta",
          "type": "real",
          "description": "abseta"
        },
        {
          "name": "pt",
          "type": "real",
          "description": "pt"
        },
        {
          "name": "syst",
          "type": "string",
          "description": "systematic variation (nom, up, down)"
        }
      ],
      "output": {
        "name": "eff_data",
        "type": "real",
        "description": "eff_data"
      },
      "generic_formulas": null,
      "data": {
        "nodetype": "category",
        "input": "syst",
        "content": [
          {
            "key": "nom",
            "value": {
              "nodetype": "binning",
              "input": "abseta",
              "edges": [
                0.0,
                0.8,
                1.6,
                2.4
              ],
              "content": [
                {
                  "nodetype": "binning",
                  "input": "pt",
                  "edges": [
                    0.0,
                    10.0,
                    20.0,
                    23.0,
                    25.0,
                    30.0,
                    40.0,
                    50.0,
                    100.0,
                    200.0
                  ],
                  "content": [
                    0.0,
                    8.195377806916898e-05,
                    0.01762114537444934,
                    0.845389507154213,
                    0.9121880998080614,
                    0.9184549356223176,
                    0.9195402298850575,
                    0.9146658952849291,
                    0.9113607990012484
                  ],
                  "flow": "clamp"
                },
                {
                  "nodetype": "binning",
                  "input": "pt",
                  "edges": [
                    0.0,
                    10.0,
                    20.0,
                    23.0,
                    25.0,
                    30.0,
                    40.0,
                    50.0,
                    100.0,
                    200.0
                  ],
                  "content": [
                    0.0,
                    0.0018713680685511671,
                    0.023502151605428664,
                    0.790583619421285,
                    0.8839812741705679,
                    0.9027991023975434,
                    0.9010360290706665,
                    0.8886602044881158,
                    0.8469957560866652
                  ],
                  "flow": "clamp"
                },
                {
                  "nodetype": "binning",
                  "input": "pt",
                  "edges": [
                    0.0,
                    10.0,
                    20.0,
                    23.0,
                    25.0,
                    30.0,
                    40.0,
                    50.0,
                    100.0,
                    200.0
                  ],
                  "content": [
                    0.0,
                    0.0014308198597796538,
                    0.05015353121801433,
                    0.6231633535004322,
                    0.7736173136379251,
                    0.8129434530208557,
                    0.8151041666666666,
                    0.8347730700671877,
                    0.8314977973568282
                  ],
                  "flow": "clamp"
                }
              ],
              "flow": "clamp"
            }
          },
          {
            "key": "up",
            "value": {
              "nodetype": "binning",
              "input": "abseta",
              "edges": [
                0.0,
                0.8,
                1.6,
                2.4
              ],
              "content": [
                {
                  "nodetype": "binning",
                  "input": "pt",
                  "edges": [
                    0.0,
                    10.0,
                    20.0,
                    23.0,
                    25.0,
                    30.0,
                    40.0,
                    50.0,
                    100.0,
                    200.0
                  ],
                  "content": [
                    0.0,
                    0.000176354530551105,
                    0.01978366076767933,
                    0.870351542172679,
                    0.9296086354534281,
                    0.9312490349830701,
                    0.9338557868717166,
                    0.9239175394429131,
                    0.9279269772521643
                  ],
                  "flow": "clamp"
                },
                {
                  "nodetype": "binning",
                  "input": "pt",
                  "edges": [
                    0.0,
                    10.0,
                    20.0,
                    23.0,
                    25.0,
                    30.0,
                    40.0,
                    50.0,
                    100.0,
                    200.0
                  ],
                  "content": [
                    0.0,
                    0.0024025738614956915,
                    0.02676880337406852,
                    0.8175777056723296,
                    0.9023949088078563,
                    0.9170815390783389,
                    0.9179985954583786,
                    0.8992177747030312,
                    0.8656906552167107
                  ],
                  "flow": "clamp"
                },
                {
                  "nodetype": "binning",
                  "input": "pt",
                  "edges": [
                    0.0,
                    10.0,
                    20.0,
                    23.0,
                    25.0,
                    30.0,
                    40.0,
                    50.0,
                    100.0,
                    200.0
                  ],
                  "content": [
                    0.0,
                    0.001963784870945699,
                    0.057252121819745795,
                    0.6528795576960255,
                    0.7968020056786432,
                    0.8314098660428847,
                    0.835878722777453,
                    0.8492684549740203,
                    0.8604563110863572
                  ],
                  "flow": "clamp"
                }
              ],
              "flow": "clamp"
            }
          },
          {
            "key": "down",
            "value": {
              "nodetype": "binning",
              "input": "abseta",
              "edges": [
                0.0,
                0.8,
                1.6,
                2.4
              ],
              "content": [
                {
                  "nodetype": "binning",
                  "input": "pt",
                  "edges": [
                    0.0,
                    10.0,
                    20.0,
                    23.0,
                    25.0,
                    30.0,
                    40.0,
                    50.0,
                    100.0,
                    200.0
                  ],
                  "content": [
                    0.0,
                    -1.2446974412767023e-05,
                    0.01545862998121935,
                    0.8204274721357471,
                    0.8947675641626947,
                    0.9056608362615651,
                    0.9052246728983984,
                    0.9054142511269452,
                    0.8947946207503326
                  ],
                  "flow": "clamp"
                },
                {
                  "nodetype": "binning",
                  "input": "pt",
                  "edges": [
                    0.0,
                    10.0,
                    20.0,
                    23.0,
                    25.0,
                    30.0,
                    40.0,
                    50.0,
                    100.0,
                    200.0
                  ],
                  "content": [
                    0.0,
                    0.0013401622756066428,
                    0.02023549983678881,
                    0.7635895331702404,
                    0.8655676395332795,
                    0.8885166657167478,
                    0.8840734626829544,
                    0.8781026342732003,
                    0.8283008569566197
                  ],
                  "flow": "clamp"
                },
                {
                  "nodetype": "binning",
                  "input": "pt",
                  "edges": [
                    0.0,
                    10.0,
                    20.0,
                    23.0,
                    25.0,
                    30.0,
                    40.0,
                    50.0,
                    100.0,
                    200.0
                  ],
                  "content": [
                    0.0,
                    0.0008978548486136085,
                    0.043054940616282865,
                    0.5934471493048389,
                    0.7504326215972069,
                    0.7944770399988267,
                    0.7943296105558803,
                    0.8202776851603552,
                    0.8025392836272991
                  ],
                  "flow": "clamp"
                }
              ],
              "flow": "clamp"
            }
          }
        ],
        "default": null
      }
    },
    {
      "name": "Mu23El12_MC",
      "description": "",
      "version": 1,
      "inputs": [
        {
          "name": "abseta",
          "type": "real",
          "description": "abseta"
        },
        {
          "name": "pt",
          "type": "real",
          "description": "pt"
        },
        {
          "name": "syst",
          "type": "string",
          "description": "systematic variation (nom, up, down)"
        }
      ],
      "output": {
        "name": "eff_mc",
        "type": "real",
        "description": "eff_mc"
      },
      "generic_formulas": null,
      "data": {
        "nodetype": "category",
        "input": "syst",
        "content": [
          {
            "key": "nom",
            "value": {
              "nodetype": "binning",
              "input": "abseta",
              "edges": [
                0.0,
                0.8,
                1.6,
                2.4
              ],
              "content": [
                {
                  "nodetype": "binning",
                  "input": "pt",
                  "edges": [
                    0.0,
                    10.0,
                    20.0,
                    23.0,
                    25.0,
                    30.0,
                    40.0,
                    50.0,
                    100.0,
                    200.0
                  ],
                  "content": [
                    0.0,
                    0.0001340519772671186,
                    0.01988603542755092,
                    0.911101602711329,
                    0.9549685441415536,
                    0.9572015836870569,
                    0.9560470871611871,
                    0.9541995706076101,
                    0.9480702131055972
                  ],
                  "flow": "clamp"
                },
                {
                  "nodetype": "binning",
                  "input": "pt",
                  "edges": [
                    0.0,
                    10.0,
                    20.0,
                    23.0,
                    25.0,
                    30.0,
                    40.0,
                    50.0,
                    100.0,
                    200.0
                  ],
                  "content": [
                    0.0,
                    0.0007963393756306312,
                    0.025246956177794287,
                    0.8402438909952494,
                    0.9119845761647277,
                    0.9213552395632663,
                    0.9275213957115669,
                    0.9297746981944673,
                    0.9271494184365242
                  ],
                  "flow": "clamp"
                },
                {
                  "nodetype": "binning",
                  "input": "pt",
                  "edges": [
                    0.0,
                    10.0,
                    20.0,
                    23.0,
                    25.0,
                    30.0,
                    40.0,
                    50.0,
                    100.0,
                    200.0
                  ],
                  "content": [
                    0.0,
                    0.0012819102468139784,
                    0.04040772181090268,
                    0.7174803072430254,
                    0.8287737793501552,
                    0.8475809840232038,
                    0.8557565344891385,
                    0.8645214287108532,
                    0.8591641316362902
                  ],
                  "flow": "clamp"
                }
              ],
              "flow": "clamp"
            }
          },
          {
            "key": "up",
            "value": {
              "nodetype": "binning",
              "input": "abseta",
              "edges": [
                0.0,
                0.8,
                1.6,
                2.4
              ],
              "content": [
                {
                  "nodetype": "binning",
                  "input": "pt",
                  "edges": [
                    0.0,
                    10.0,
                    20.0,
                    23.0,
                    25.0,
                    30.0,
                    40.0,
                    50.0,
                    100.0,
                    200.0
                  ],
                  "content": [
                    0.0,
                    0.0002717299159681272,
                    0.02069132695223893,
                    0.9184436388933507,
                    0.9603056365086786,
                    0.96449605878651,
                    0.9689593780697194,
                    0.9746372784186361,
                    1.000135447963497
                  ],
                  "flow": "clamp"
                },
                {
                  "nodetype": "binning",
                  "input": "pt",
                  "edges": [
                    0.0,
                    10.0,
                    20.0,
                    23.0,
                    25.0,
                    30.0,
                    40.0,
                    50.0,
                    100.0,
                    200.0
                  ],
                  "content": [
                    0.0,
                    0.0012235215889590187,
                    0.030762651893022304,
                    0.8520490934038825,
                    0.9233425931236401,
                    0.925015944119709,
                    0.9319221631003791,
                    0.936863856358462,
                    0.9573515665697422
                  ],
                  "flow": "clamp"
                },
                {
                  "nodetype": "binning",
                  "input": "pt",
                  "edges": [
                    0.0,
                    10.0,
                    20.0,
                    23.0,
                    25.0,
                    30.0,
                    40.0,
                    50.0,
                    100.0,
                    200.0
                  ],
                  "content": [
                    0.0,
                    0.0016696543747491091,
                    0.052228090732070964,
                    0.7315169061959897,
                    0.8356226937048117,
                    0.8734896441513329,
                    0.8745314067669485,
                    0.9213663185099313,
                    0.9346067521832744
                  ],
                  "flow": "clamp"
                }
              ],
              "flow": "clamp"
            }
          },
          {
            "key": "down",
            "value": {
              "nodetype": "binning",
              "input": "abseta",
              "edges": [
                0.0,
                0.8,
                1.6,
                2.4
              ],
              "content": [
                {
                  "nodetype": "binning",
                  "input": "pt",
                  "edges": [
                    0.0,
                    10.0,
                    20.0,
                    23.0,
                    25.0,
                    30.0,
                    40.0,
                    50.0,
                    100.0,
                    200.0
                  ],
                  "content": [
                    0.0,
                    -3.625961433890014e-06,
                    0.019080743902862914,
                    0.9037595665293073,
                    0.9496314517744286,
                    0.9499071085876037,
                    0.9431347962526548,
                    0.933761862796584,
                    0.8960049782476975
                  ],
                  "flow": "clamp"
                },
                {
                  "nodetype": "binning",
                  "input": "pt",
                  "edges": [
                    0.0,
                    10.0,
                    20.0,
                    23.0,
                    25.0,
                    30.0,
                    40.0,
                    50.0,
                    100.0,
                    200.0
                  ],
                  "content": [
                    0.0,
                    0.0003691571623022437,
                    0.01973126046256627,
                    0.8284386885866164,
                    0.9006265592058154,
                    0.9176945350068235,
                    0.9231206283227547,
                    0.9226855400304727,
                    0.8969472703033062
                  ],
                  "flow": "clamp"
                },
                {
                  "nodetype": "binning",
                  "input": "pt",
                  "edges": [
                    0.0,
                    10.0,
                    20.0,
                    23.0,
                    25.0,
                    30.0,
                    40.0,
                    50.0,
                    100.0,
                    200.0
                  ],
                  "content": [
                    0.0,
                    0.0008941661188788476,
                    0.028587352889734394,
                    0.703443708290061,
                    0.8219248649954987,
                    0.8216723238950747,
                    0.8369816622113284,
                    0.8076765389117752,
                    0.7837215110893061
                  ],
                  "flow": "clamp"
                }
              ],
              "flow": "clamp"
            }
          }
        ],
        "default": null
      }
    }
  ],
  "compound_corrections": null
}