{
    "DYJets_MG": {
        "isMC": 1,
        "PD": "DYto2L-4Jets_MLL-50_TuneCP5_13p6TeV_madgraphMLM-pythia8",
        "xsec": 6275.1,
        "nmc": 254295366.0,
        "sumsign": 254295366.0,
        "sumW": 3356011957034.408
    },
    "DYJets": {
        "isMC": 1,
        "PD": "DYto2L-2Jets_MLL-50_TuneCP5_13p6TeV_amcatnloFXFX-pythia8",
        "xsec": 6275.1,
        "nmc": 319825084.0,
        "sumsign": 212904600.0,
        "sumW": 5701587682975.781
    },
    "WJets_MG": {
        "isMC": 1,
        "PD": "WtoLNu-4Jets_TuneCP5_13p6TeV_madgraphMLM-pythia8",
        "xsec": 63396,
        "nmc": 341646395.0,
        "sumsign": 341646395.0,
        "sumW": 43097238687592.195
    },
    "WJets": {
        "isMC": 1,
        "PD": "WtoLNu-2Jets_TuneCP5_13p6TeV_amcatnloFXFX-pythia8",
        "xsec": 63396,
        "nmc": 281543551.0,
        "sumsign": 191351565.0,
        "sumW": 49651697785293.984
    },
    "TTJJ_powheg": {
        "isMC": 1,
        "PD": "TTto4Q_TuneCP5_13p6TeV_powheg-pythia8",
        "xsec_formula": "923.6*0.6741*0.6741",
        "nmc": 187745623.0,
        "sumsign": 186226355.0,
        "sumW": 65210885230.94803,
        "xsec": 419.6938241160001
    },
    "TTJJ_Vcb_powheg": {
        "isMC": 1,
        "PD": "TTto4Q_Vcb_TuneCP5_13p6TeV_powheg-pythia8",
        "xsec_formula": "923.6*0.6741*0.6741*0.04183 * 0.04183 / 2 *2",
        "nmc": 11437200.0,
        "sumsign": 11345440.0,
        "sumW": 3972832877.1435547,
        "xsec": 0.7343588070837646
    },
    "TTJJ_powheg_mTop171p5": {
        "isMC": 1,
        "PD": "TTto4Q_MT-171p5_TuneCP5_13p6TeV_powheg-pythia8",
        "xsec_formula": "923.6*0.6741*0.6741",
        "nmc": 71667616.0,
        "sumsign": 71085368.0,
        "sumW": 25579571157.418213,
        "xsec": 419.6938241160001
    },
    "TTJJ_powheg_mTop173p5": {
        "isMC": 1,
        "PD": "TTto4Q_MT-173p5_TuneCP5_13p6TeV_powheg-pythia8",
        "xsec_formula": "923.6*0.6741*0.6741",
        "nmc": 74724824.0,
        "sumsign": 74121796.0,
        "sumW": 25260856465.161133,
        "xsec": 419.6938241160001
    },
    "TTJJ_powheg_hDampUp": {
        "isMC": 1,
        "PD": "TTto4Q_Hdamp-418_TuneCP5_13p6TeV_powheg-pythia8",
        "xsec_formula": "923.6*0.6741*0.6741",
        "nmc": 73588304.0,
        "sumsign": 73249114.0,
        "sumW": 25562402840.73535,
        "xsec": 419.6938241160001
    },
    "TTJJ_powheg_hDampDown": {
        "isMC": 1,
        "PD": "TTto4Q_Hdamp-158_TuneCP5_13p6TeV_powheg-pythia8",
        "xsec_formula": "923.6*0.6741*0.6741",
        "nmc": 79760788.0,
        "sumsign": 78460682.0,
        "sumW": 27700542822.328003,
        "xsec": 419.6938241160001
    },
    "TTJJ_powheg_CP5Up": {
        "isMC": 1,
        "PD": "TTto4Q_TuneCP5Up_13p6TeV_powheg-pythia8",
        "xsec_formula": "923.6*0.6741*0.6741",
        "nmc": 73414336.0,
        "sumsign": 72821940.0,
        "sumW": 25500059707.633667,
        "xsec": 419.6938241160001
    },
    "TTJJ_powheg_CP5Down": {
        "isMC": 1,
        "PD": "TTto4Q_TuneCP5Down_13p6TeV_powheg-pythia8",
        "xsec_formula": "923.6*0.6741*0.6741",
        "nmc": 75167944.0,
        "sumsign": 74557536.0,
        "sumW": 26107813382.25879,
        "xsec": 419.6938241160001
    },
    "TTLJ_powheg": {
        "isMC": 1,
        "PD": "TTtoLNu2Q_TuneCP5_13p6TeV_powheg-pythia8",
        "xsec_formula": "923.6*2*3*0.1086*0.6741",
        "nmc": 275339453.0,
        "sumsign": 273110457.0,
        "sumW": 92051059400.35071,
        "xsec": 405.685352016
    },
    "TTLJ_powheg_mTop171p5": {
        "isMC": 1,
        "PD": "TTtoLNu2Q_MT-171p5_TuneCP5_13p6TeV_powheg-pythia8",
        "xsec_formula": "923.6*2*3*0.1086*0.6741",
        "nmc": 106574300.0,
        "sumsign": 105708256.0,
        "sumW": 36612793855.62305,
        "xsec": 405.685352016
    },
    "TTLJ_powheg_mTop173p5": {
        "isMC": 1,
        "PD": "TTtoLNu2Q_MT-173p5_TuneCP5_13p6TeV_powheg-pythia8",
        "xsec_formula": "923.6*2*3*0.1086*0.6741",
        "nmc": 108466728.0,
        "sumsign": 107593038.0,
        "sumW": 35293744123.80084,
        "xsec": 405.685352016
    },
    "TTLJ_powheg_hDampUp": {
        "isMC": 1,
        "PD": "TTtoLNu2Q_Hdamp-418_TuneCP5_13p6TeV_powheg-pythia8",
        "xsec_formula": "923.6*2*3*0.1086*0.6741",
        "nmc": 108814065.0,
        "sumsign": 108309551.0,
        "sumW": 36381286596.222046,
        "xsec": 405.685352016
    },
    "TTLJ_powheg_hDampDown": {
        "isMC": 1,
        "PD": "TTtoLNu2Q_Hdamp-158_TuneCP5_13p6TeV_powheg-pythia8",
        "xsec_formula": "923.6*2*3*0.1086*0.6741",
        "nmc": 105603983.0,
        "sumsign": 103883007.0,
        "sumW": 35301419581.09506,
        "xsec": 405.685352016
    },
    "TTLJ_powheg_CP5Up": {
        "isMC": 1,
        "PD": "TTtoLNu2Q_TuneCP5Up_13p6TeV_powheg-pythia8",
        "xsec_formula": "923.6*2*3*0.1086*0.6741",
        "nmc": 107642765.0,
        "sumsign": 106772963.0,
        "sumW": 35987506547.449585,
        "xsec": 405.685352016
    },
    "TTLJ_powheg_CP5Down": {
        "isMC": 1,
        "PD": "TTtoLNu2Q_TuneCP5Down_13p6TeV_powheg-pythia8",
        "xsec_formula": "923.6*2*3*0.1086*0.6741",
        "nmc": 108790299.0,
        "sumsign": 107909733.0,
        "sumW": 36370651462.309204,
        "xsec": 405.685352016
    },
    "TTLJ_Vcb_powheg": {
        "isMC": 1,
        "PD": "TTtoLNuCB_TuneCP5_13p6TeV_powheg-pythia8",
        "xsec_formula": "923.6*2*3*0.1086*0.6741* 0.04183 * 0.04183 / 2",
        "nmc": 9979616.0,
        "sumsign": 9898504.0,
        "sumW": 3336261048.6884766,
        "xsec": 0.35492374921805436
    },
    "TTLL_powheg": {
        "isMC": 1,
        "PD": "TTto2L2Nu_TuneCP5_13p6TeV_powheg-pythia8",
        "xsec_formula": "923.6*3*0.1086*3*0.1086",
        "nmc": 84715417.0,
        "sumsign": 84028747.0,
        "sumW": 6815058849.686813,
        "xsec": 98.03611310400001
    },
    "TTLL_powheg_mTop171p5": {
        "isMC": 1,
        "PD": "TTto2L2Nu_MT-171p5_TuneCP5_13p6TeV_powheg-pythia8",
        "xsec_formula": "923.6*3*0.1086*3*0.1086",
        "nmc": 33779592.0,
        "sumsign": 33504082.0,
        "sumW": 2792374238.529419,
        "xsec": 98.03611310400001
    },
    "TTLL_powheg_mTop173p5": {
        "isMC": 1,
        "PD": "TTto2L2Nu_MT-173p5_TuneCP5_13p6TeV_powheg-pythia8",
        "xsec_formula": "923.6*3*0.1086*3*0.1086",
        "nmc": 34942166.0,
        "sumsign": 34661970.0,
        "sumW": 2736014750.092392,
        "xsec": 98.03611310400001
    },
    "TTLL_powheg_hDampUp": {
        "isMC": 1,
        "PD": "TTto2L2Nu_Hdamp-418_TuneCP5_13p6TeV_powheg-pythia8",
        "xsec_formula": "923.6*3*0.1086*3*0.1086",
        "nmc": 33381504.0,
        "sumsign": 33226736.0,
        "sumW": 2685654010.250366,
        "xsec": 98.03611310400001
    },
    "TTLL_powheg_hDampDown": {
        "isMC": 1,
        "PD": "TTto2L2Nu_Hdamp-158_TuneCP5_13p6TeV_powheg-pythia8",
        "xsec_formula": "923.6*3*0.1086*3*0.1086",
        "nmc": 33569906.0,
        "sumsign": 33022548.0,
        "sumW": 2700286895.455719,
        "xsec": 98.03611310400001
    },
    "TTLL_powheg_CP5Up": {
        "isMC": 1,
        "PD": "TTto2L2Nu_TuneCP5Up_13p6TeV_powheg-pythia8",
        "xsec_formula": "923.6*3*0.1086*3*0.1086",
        "nmc": 34267798.0,
        "sumsign": 33989900.0,
        "sumW": 2756713351.8600464,
        "xsec": 98.03611310400001
    },
    "TTLL_powheg_CP5Down": {
        "isMC": 1,
        "PD": "TTto2L2Nu_TuneCP5Down_13p6TeV_powheg-pythia8",
        "xsec_formula": "923.6*3*0.1086*3*0.1086",
        "nmc": 33116945.0,
        "sumsign": 32849009.0,
        "sumW": 2664182645.5997467,
        "xsec": 98.03611310400001
    },
    "ST_sch_top_Lep": {
        "isMC": 1,
        "PD": "TBbartoLplusNuBbar-s-channel-4FS_TuneCP5_13p6TeV_amcatnlo-pythia8",
        "xsec_formula": "6.72748*0.1086*3",
        "nmc": 4363850.0,
        "sumsign": 2685976.0,
        "sumW": 9937726.377031326,
        "note": "NLO parmetrization @ 13.6TeV",
        "xsec": 2.191812984
    },
    "ST_sch_antitop_Lep": {
        "isMC": 1,
        "PD": "TbarBtoLminusNuB-s-channel-4FS_TuneCP5_13p6TeV_amcatnlo-pythia8",
        "xsec_formula": "4.24192*0.1086*3",
        "nmc": 2762668.0,
        "sumsign": 1700756.0,
        "sumW": 3945012.9158239365,
        "note": "NLO parmetrization @ 13.6TeV",
        "xsec": 1.3820175360000002
    },
    "ttHtobb_M125": {
        "isMC": 1,
        "PD": "TTHto2B_M-125_TuneCP5_13p6TeV_powheg-pythia8",
        "xsec": 0.331968,
        "xsec_formula": "0.57*0.5824",
        "nmc": 11099294.0,
        "sumsign": 10856130.0,
        "sumW": 6364916.185857654
    },
    "ttHtoNonbb_M125": {
        "isMC": 1,
        "PD": "TTHtoNon2B_M-125_TuneCP5_13p6TeV_powheg-pythia8",
        "xsec": 0.23803199999999997,
        "xsec_formula": "0.57*(1-0.5824)",
        "nmc": 13955780.0,
        "sumsign": 13649278.0,
        "sumW": 8002530.410696149
    },
    "ttZtoQQ": {
        "isMC": 1,
        "PD": "TTZ-ZtoQQ-1Jets_TuneCP5_13p6TeV_amcatnloFXFX-pythia8",
        "xsec": 0.6603,
        "nmc": 1334574.0,
        "sumsign": 527226.0,
        "sumW": 1709477.7973980904
    },
    "ttZtoNuNu": {
        "isMC": 1,
        "PD": "TTNuNu_TuneCP5_13p6TeV_amcatnlo-pythia8",
        "xsec": 0.1638,
        "nmc": 1746360.0,
        "sumsign": 906626.0,
        "sumW": 285821.52848523855
    },
    "ttZtoLL_MLL4to50": {
        "isMC": 1,
        "PD": "TTLL_MLL-4to50_TuneCP5_13p6TeV_amcatnlo-pythia8",
        "xsec": 0.03949,
        "nmc": 1049999.0,
        "sumsign": 582589.0,
        "sumW": 41403.1594504267
    },
    "ttZtoLL_MLL50toInf": {
        "isMC": 1,
        "PD": "TTLL_MLL-50_TuneCP5_13p6TeV_amcatnlo-pythia8",
        "xsec": 0.08646,
        "nmc": 1343867.0,
        "sumsign": 700033.0,
        "sumW": 116162.55919010937
    },
    "ttWtoLNu": {
        "isMC": 1,
        "PD": "TTLNu-1Jets_TuneCP5_13p6TeV_amcatnloFXFX-pythia8",
        "xsec": 0.2505,
        "nmc": 335985.0,
        "sumsign": 174427.0,
        "sumW": 151584.8843652606
    },
    "ttWtoLNu_EWK": {
        "isMC": 1,
        "PD": "TTLNu-EWK_TuneCP5_13p6TeV_amcatnlo-pythia8",
        "xsec": 0.01769,
        "nmc": 599291.0,
        "sumsign": 579255.0,
        "sumW": 10624.044316196814
    },
    "ST_tW_top_Semilep": {
        "isMC": 1,
        "PD": "TWminustoLNu2Q_TuneCP5_13p6TeV_powheg-pythia8",
        "xsec_formula": "(87.9*0.5)*(2*3*0.1086*0.6741)",
        "nmc": 15886044.0,
        "sumsign": 15885464.0,
        "sumW": 571676548.0262146,
        "xsec": 19.304754462000002
    },
    "ST_tW_antitop_Semilep": {
        "isMC": 1,
        "PD": "TbarWplustoLNu2Q_TuneCP5_13p6TeV_powheg-pythia8",
        "xsec_formula": "(87.9*0.5)*(2*3*0.1086*0.6741)",
        "nmc": 17272926.0,
        "sumsign": 17272270.0,
        "sumW": 622749987.0205688,
        "xsec": 19.304754462000002
    },
    "ST_tW_top_Lep": {
        "isMC": 1,
        "PD": "TWminusto2L2Nu_TuneCP5_13p6TeV_powheg-pythia8",
        "xsec_formula": "(87.9*0.5)*(3*0.1086*3*0.1086)",
        "nmc": 8466410.0,
        "sumsign": 8466108.0,
        "sumW": 32161305.32750702,
        "xsec": 4.6651008780000005
    },
    "ST_tW_antitop_Lep": {
        "isMC": 1,
        "PD": "TbarWplusto2L2Nu_TuneCP5_13p6TeV_powheg-pythia8",
        "xsec_formula": "(87.9*0.5)*(3*0.1086*3*0.1086)",
        "nmc": 8555460.0,
        "sumsign": 8555134.0,
        "sumW": 32560411.617439747,
        "xsec": 4.6651008780000005
    },
    "ST_tW_top_Fullyhad": {
        "isMC": 1,
        "PD": "TWminusto4Q_TuneCP5_13p6TeV_powheg-pythia8",
        "xsec_formula": "(87.9*0.5)*(0.6741*0.6741)",
        "nmc": 13999320.0,
        "sumsign": 13998764.0,
        "sumW": 229602125.99900818,
        "xsec": 19.971355099500002
    },
    "ST_tW_antitop_Fullyhad": {
        "isMC": 1,
        "PD": "TbarWplusto4Q_TuneCP5_13p6TeV_powheg-pythia8",
        "xsec_formula": "(87.9*0.5)*(0.6741*0.6741)",
        "nmc": 12600658.0,
        "sumsign": 12600194.0,
        "sumW": 207051424.73247528,
        "xsec": 19.971355099500002
    },
    "ST_tch_top": {
        "isMC": 1,
        "PD": "TBbarQ_t-channel_4FS_TuneCP5_13p6TeV_powheg-madspin-pythia8",
        "xsec": 145,
        "nmc": 10153433.0,
        "sumsign": 9345833.0,
        "sumW": 1264425777.2239075
    },
    "ST_tch_antitop": {
        "isMC": 1,
        "PD": "TbarBQ_t-channel_4FS_TuneCP5_13p6TeV_powheg-madspin-pythia8",
        "xsec": 87.2,
        "nmc": 5206568.0,
        "sumsign": 4814586.0,
        "sumW": 394682438.7607269
    },
    "WWto2L2Nu": {
        "isMC": 1,
        "PD": "WWto2L2Nu_TuneCP5_13p6TeV_powheg-pythia8",
        "xsec_formula": "1.673*9",
        "nmc": 22208244.0,
        "sumsign": 22203808.0,
        "sumW": 261816204.06481934,
        "note": "need check the xsec",
        "xsec": 15.057
    },
    "WWtoLNu2Q": {
        "isMC": 1,
        "PD": "WWtoLNu2Q_TuneCP5_13p6TeV_powheg-pythia8",
        "xsec_formula": "1.673/0.1086*0.6741*6",
        "nmc": 94431936.0,
        "sumsign": 94413272.0,
        "sumW": 4621463467.350311,
        "note": "need check the xsec",
        "xsec": 62.30769613259669
    },
    "WWto4Q": {
        "isMC": 1,
        "PD": "WWto4Q_TuneCP5_13p6TeV_powheg-pythia8",
        "xsec_formula": "1.6741/0.1086/0.1086*0.6741*0.6741",
        "nmc": 96515525.0,
        "sumsign": 96496437.0,
        "sumW": 4902028496.701115,
        "note": "need check the xsec",
        "xsec": 64.50158700054943
    },
    "WZto3LNu": {
        "isMC": 1,
        "PD": "WZto3LNu_TuneCP5_13p6TeV_powheg-pythia8",
        "xsec_formula": "(0.3459+0.2366)*9",
        "nmc": 9779090.0,
        "sumsign": 9760064.0,
        "sumW": 48154010.44882202,
        "note": "need check the xsec",
        "xsec": 5.2425
    },
    "WZto2L2Q": {
        "isMC": 1,
        "PD": "WZto2L2Q_TuneCP5_13p6TeV_powheg-pythia8",
        "xsec_formula": "(0.3459+0.2366)/0.1086*0.6741",
        "nmc": 14965986.0,
        "sumsign": 14950220.0,
        "sumW": 113263461.60580635,
        "note": "need check the xsec",
        "xsec": 3.615683701657459
    },
    "WZtoLNu2Q": {
        "isMC": 1,
        "PD": "WZtoLNu2Q_TuneCP5_13p6TeV_powheg-pythia8",
        "xsec_formula": "(0.3459+0.2366)*3/0.033658*0.69911",
        "nmc": 30166518.0,
        "sumsign": 30153688.0,
        "sumW": 478750100.00496674,
        "note": "need check the xsec",
        "xsec": 36.29730598966071
    },
    "ZZto4L": {
        "isMC": 1,
        "PD": "ZZto4L_TuneCP5_13p6TeV_powheg-pythia8",
        "xsec_formula": "0.1633*9",
        "nmc": 52258920.0,
        "sumsign": 51715156.0,
        "sumW": 72661346.26202297,
        "note": "need check the xsec",
        "xsec": 1.4697
    },
    "ZZto2Nu2Q": {
        "isMC": 1,
        "PD": "ZZto2Nu2Q_TuneCP5_13p6TeV_powheg-pythia8",
        "xsec_formula": "0.1633*2/0.033658*0.69911/0.033658*0.2",
        "nmc": 10280002.0,
        "sumsign": 10263806.0,
        "sumW": 49610310.91621208,
        "note": "need check the xsec",
        "xsec": 40.310211624522005
    },
    "ZZto2L2Q": {
        "isMC": 1,
        "PD": "ZZto2L2Q_TuneCP5_13p6TeV_powheg-pythia8",
        "xsec_formula": "0.1633*2*3/0.033658*0.69911",
        "nmc": 51456532.0,
        "sumsign": 51139906.0,
        "sumW": 349362270.57016563,
        "note": "need check the xsec",
        "xsec": 20.351416542872425
    },
    "ZZto2L2Nu": {
        "isMC": 1,
        "PD": "ZZto2L2Nu_TuneCP5_13p6TeV_powheg-pythia8",
        "xsec_formula": "0.1633*2*3/0.033658*0.2",
        "nmc": 50835790.0,
        "sumsign": 50723608.0,
        "sumW": 52402051.9545908,
        "note": "need check the xsec",
        "xsec": 5.822092815972429
    },
    "QCDB_HT40to100": {
        "isMC": 1,
        "PD": "QCDB-4Jets_HT-40to100_TuneCP5_13p6TeV_madgraphMLM-pythia8",
        "xsec": 13050000,
        "nmc": 100539903.0,
        "sumsign": 100539903.0,
        "sumW": 4815660079124792.0
    },
    "QCDB_HT100to200": {
        "isMC": 1,
        "PD": "QCDB-4Jets_HT-100to200_TuneCP5_13p6TeV_madgraphMLM-pythia8",
        "xsec": 1196000,
        "nmc": 99301000.0,
        "sumsign": 99301000.0,
        "sumW": 684223574708003.0
    },
    "QCDB_HT200to400": {
        "isMC": 1,
        "PD": "QCDB-4Jets_HT-200to400_TuneCP5_13p6TeV_madgraphMLM-pythia8",
        "xsec": 100800,
        "nmc": 89727735.0,
        "sumsign": 89727735.0,
        "sumW": 67298189852104.31
    },
    "QCDB_HT400to600": {
        "isMC": 1,
        "PD": "QCDB-4Jets_HT-400to600_TuneCP5_13p6TeV_madgraphMLM-pythia8",
        "xsec": 4904,
        "nmc": 43138269.0,
        "sumsign": 43138269.0,
        "sumW": 1888954747638.6953
    },
    "QCDB_HT600to800": {
        "isMC": 1,
        "PD": "QCDB-4Jets_HT-400to600_TuneCP5_13p6TeV_madgraphMLM-pythia8",
        "xsec": 656.1,
        "nmc": 43138269.0,
        "sumsign": 43138269.0,
        "sumW": 1888954747638.6953
    },
    "QCDB_HT800to1000": {
        "isMC": 1,
        "PD": "QCDB-4Jets_HT-800to1000_TuneCP5_13p6TeV_madgraphMLM-pythia8",
        "xsec": 139.9,
        "nmc": 10012514.0,
        "sumsign": 10012514.0,
        "sumW": 14204409309.747925
    },
    "QCDB_HT1000to1500": {
        "isMC": 1,
        "PD": "QCDB-4Jets_HT-1000to1500_TuneCP5_13p6TeV_madgraphMLM-pythia8",
        "xsec": 54.84,
        "nmc": 707858.0,
        "sumsign": 707858.0,
        "sumW": 404985021.6690674
    },
    "QCDB_HT1500to2000": {
        "isMC": 1,
        "PD": "QCDB-4Jets_HT-1500to2000_TuneCP5_13p6TeV_madgraphMLM-pythia8",
        "xsec": 4.741,
        "nmc": 741997.0,
        "sumsign": 741997.0,
        "sumW": 37725043.07924652
    },
    "QCD_HT70to100": {
        "isMC": 1,
        "PD": "QCD-4Jets_HT-70to100_TuneCP5_13p6TeV_madgraphMLM-pythia8",
        "xsec": 58500000,
        "nmc": 64668546.0,
        "sumsign": 64668546.0,
        "sumW": 1.9735734289614384e+16
    },
    "QCD_HT100to200": {
        "isMC": 1,
        "PD": "QCD-4Jets_HT-100to200_TuneCP5_13p6TeV_madgraphMLM-pythia8",
        "xsec": 0,
        "nmc": 69742765.0,
        "sumsign": 69742765.0,
        "sumW": 1.1422381552852032e+16
    },
    "QCD_HT200to400": {
        "isMC": 1,
        "PD": "QCD-4Jets_HT-200to400_TuneCP5_13p6TeV_madgraphMLM-pythia8",
        "xsec": 1961000,
        "nmc": 70275585.0,
        "sumsign": 70275585.0,
        "sumW": 1208768870558997.0
    },
    "QCD_HT400to600": {
        "isMC": 1,
        "PD": "QCD-4Jets_HT-400to600_TuneCP5_13p6TeV_madgraphMLM-pythia8",
        "xsec": 95620,
        "nmc": 68707093.0,
        "sumsign": 68707091.0,
        "sumW": 71848513576506.69
    },
    "QCD_HT600to800": {
        "isMC": 1,
        "PD": "QCD-4Jets_HT-600to800_TuneCP5_13p6TeV_madgraphMLM-pythia8",
        "xsec": 13540,
        "nmc": 63298004.0,
        "sumsign": 63298004.0,
        "sumW": 10199547397722.234
    },
    "QCD_HT800to1000": {
        "isMC": 1,
        "PD": "QCD-4Jets_HT-800to1000_TuneCP5_13p6TeV_madgraphMLM-pythia8",
        "xsec": 3033,
        "nmc": 66430382.0,
        "sumsign": 66430382.0,
        "sumW": 2523690114641.4375
    },
    "QCD_HT1000to1200": {
        "isMC": 1,
        "PD": "QCD-4Jets_HT-1000to1200_TuneCP5_13p6TeV_madgraphMLM-pythia8",
        "xsec": 883.7,
        "nmc": 70854616.0,
        "sumsign": 70854616.0,
        "sumW": 811244844915.8906
    },
    "QCD_HT1200to1500": {
        "isMC": 1,
        "PD": "QCD-4Jets_HT-1200to1500_TuneCP5_13p6TeV_madgraphMLM-pythia8",
        "xsec": 383.5,
        "nmc": 70804499.0,
        "sumsign": 70804499.0,
        "sumW": 357954980810.0845
    },
    "QCD_HT1500to2000": {
        "isMC": 1,
        "PD": "QCD-4Jets_HT-1500to2000_TuneCP5_13p6TeV_madgraphMLM-pythia8",
        "xsec": 25.14,
        "nmc": 63307771.0,
        "sumsign": 63307771.0,
        "sumW": 106344533328.8512
    },
    "QCD_HT2000toInf": {
        "isMC": 1,
        "PD": "QCD-4Jets_HT-2000_TuneCP5_13p6TeV_madgraphMLM-pythia8",
        "xsec": 25.14,
        "nmc": 65102938.0,
        "sumsign": 65102938.0,
        "sumW": 22742799881.79315
    },
    "QCD_PT30to50": {
        "isMC": 1,
        "PD": "QCD_PT-30to50_TuneCP5_13p6TeV_pythia8",
        "xsec": 113300000.0,
        "nmc": 3940000.0,
        "sumsign": 3940000.0,
        "sumW": 3940000.0
    },
    "QCD_PT50to80": {
        "isMC": 1,
        "PD": "QCD_PT-50to80_TuneCP5_13p6TeV_pythia8",
        "xsec": 16760000.0,
        "nmc": 19734680.0,
        "sumsign": 19734680.0,
        "sumW": 19734680.0
    },
    "QCD_PT80to120": {
        "isMC": 1,
        "PD": "QCD_PT-80to120_TuneCP5_13p6TeV_pythia8",
        "xsec": 2534000.0,
        "nmc": 29570284.0,
        "sumsign": 29570284.0,
        "sumW": 29573087.170908093
    },
    "QCD_PT120to170": {
        "isMC": 1,
        "PD": "QCD_PT-120to170_TuneCP5_13p6TeV_pythia8",
        "xsec": 445800.0,
        "nmc": 27570720.0,
        "sumsign": 27570720.0,
        "sumW": 27571047.858104944
    },
    "QCD_PT170to300": {
        "isMC": 1,
        "PD": "QCD_PT-170to300_TuneCP5_13p6TeV_pythia8",
        "xsec": 113700.0,
        "nmc": 27512595.0,
        "sumsign": 27512595.0,
        "sumW": 27512595.0
    },
    "QCD_PT300to470": {
        "isMC": 1,
        "PD": "QCD_PT-300to470_TuneCP5_13p6TeV_pythia8",
        "xsec": 7589.0,
        "nmc": 55587009.0,
        "sumsign": 55587009.0,
        "sumW": 55587014.532384515
    },
    "QCD_PT470to600": {
        "isMC": 1,
        "PD": "QCD_PT-470to600_TuneCP5_13p6TeV_pythia8",
        "xsec": 626.4,
        "nmc": 26324412.0,
        "sumsign": 26324412.0,
        "sumW": 26324412.739002824
    },
    "QCD_PT600to800": {
        "isMC": 1,
        "PD": "QCD_PT-600to800_TuneCP5_13p6TeV_pythia8",
        "xsec": 178.6,
        "nmc": 63833775.0,
        "sumsign": 63833775.0,
        "sumW": 63833775.0
    },
    "QCD_PT800to1000": {
        "isMC": 1,
        "PD": "QCD_PT-800to1000_TuneCP5_13p6TeV_pythia8",
        "xsec": 30.57,
        "nmc": 37957120.0,
        "sumsign": 37957120.0,
        "sumW": 37957120.0
    },
    "QCD_PT1000to1400": {
        "isMC": 1,
        "PD": "QCD_PT-1000to1400_TuneCP5_13p6TeV_pythia8",
        "xsec": 8.92,
        "nmc": 19209425.0,
        "sumsign": 19209425.0,
        "sumW": 19209425.0
    },
    "QCD_PT1400to1800": {
        "isMC": 1,
        "PD": "QCD_PT-1400to1800_TuneCP5_13p6TeV_pythia8",
        "xsec": 0.8103,
        "nmc": 5670888.0,
        "sumsign": 5670888.0,
        "sumW": 5670888.0
    },
    "QCD_PT1800to2400": {
        "isMC": 1,
        "PD": "QCD_PT-1800to2400_TuneCP5_13p6TeV_pythia8",
        "xsec": 0.1148,
        "nmc": 2914410.0,
        "sumsign": 2914410.0,
        "sumW": 2914410.0
    },
    "QCD_PT2400to3200": {
        "isMC": 1,
        "PD": "QCD_PT-2400to3200_TuneCP5_13p6TeV_pythia8",
        "xsec": 0.007542,
        "nmc": 1900526.0,
        "sumsign": 1900526.0,
        "sumW": 1900526.0
    },
    "QCD_PT3200toInf": {
        "isMC": 1,
        "PD": "QCD_PT-3200_TuneCP5_13p6TeV_pythia8",
        "xsec": 0.0002331,
        "nmc": 841736.0,
        "sumsign": 841736.0,
        "sumW": 841736.0
    },
    "GluGluHtoZZto4L": {
        "isMC": 1,
        "PD": "GluGluHtoZZto4L_M-125_TuneCP5_13p6TeV_powheg2-JHUGenV752-pythia8",
        "xsec_formula": "52.23*0.001672*3*0.033658*0.033658",
        "nmc": 1666666.0,
        "sumsign": 1666560.0,
        "sumW": 38605027.92480469,
        "xsec": 0.00029679334999899555
    },
    "Jpsito2Mu": {
        "isMC": 1,
        "PD": "Jpsito2Mu_JpsiPT8_TuneCP5_13p6TeV_pythia8",
        "nmc": 49267639.0,
        "sumsign": 49267639.0,
        "sumW": 49267639.0,
        "xsec": 0.0002
    },
    "Muon": {
        "isMC": 0,
        "periods": [
            "E",
            "F",
            "G"
        ],
        "NEvents": [
            132669236.0,
            430266972.0,
            75466643.0
        ]
    },
    "EGamma": {
        "isMC": 0,
        "periods": [
            "E",
            "F",
            "G"
        ],
        "NEvents": [
            139033757.0,
            443177147.0,
            75325249.0
        ]
    },
    "JetMET": {
        "isMC": 0,
        "periods": [
            "E",
            "F",
            "G"
        ],
        "NEvents": [
            130349052.0,
            494343266.0,
            83473691.0
        ]
    },
    "Tau": {
        "isMC": 0,
        "periods": [
            "E",
            "F",
            "G"
        ],
        "NEvents": [
            28954148.0,
            110894634.0,
            17668268.0
        ]
    }
}